aptio/__init__.py
aptio-0.0.2.dist-info/LICENSE.md
aptio-0.0.2.dist-info/METADATA
aptio-0.0.2.dist-info/WHEEL
aptio-0.0.2.dist-info/top_level.txt
aptio-0.0.2.dist-info/RECORD
