Metadata-Version: 2.1
Name: aptio
Version: 0.0.2
Summary: Aptio package manager.
Home-page: https://github.com/arye-zamir/aptio
Author: Arye Zamir
Author-email: arye.zamir@gmail.com
Classifier: Programming Language :: Python :: 3
Classifier: License :: OSI Approved :: MIT License
Classifier: Operating System :: OS Independent
Requires-Python: >=3.9, <4.0
License-File: LICENSE.md
